.gitignore
CHANGES.rst
LICENSE.txt
README.rst
bootstrap.py
buildout.cfg
setup.cfg
setup.py
js/__init__.py
js.d3_cloud.egg-info/PKG-INFO
js.d3_cloud.egg-info/SOURCES.txt
js.d3_cloud.egg-info/dependency_links.txt
js.d3_cloud.egg-info/entry_points.txt
js.d3_cloud.egg-info/namespace_packages.txt
js.d3_cloud.egg-info/not-zip-safe
js.d3_cloud.egg-info/requires.txt
js.d3_cloud.egg-info/top_level.txt
js/d3_cloud/__init__.py
js/d3_cloud/test_d3_word_cloud.txt
js/d3_cloud/resources/LICENSE
js/d3_cloud/resources/d3.layout.cloud.js
js/d3_cloud/resources/d3.layout.cloud.min.js