Metadata-Version: 1.0
Name: js.d3-cloud
Version: 1.0.1
Summary: Fanstatic packaging of D3 Word Cloud Layout
Home-page: https://github.com/davidjb/js.d3_cloud
Author: Fanstatic Developers
Author-email: fanstatic@googlegroups.com
License: BSD
Keywords: word cloud tag visualization canvas wordle d3
Platform: UNKNOWN
